{
  "vacancys": [
    {
      "title": "qwerty1",
      "description": "qwerty1",
      "city": "qwerty1",
      "image": "https://cdn.pixabay.com/photo/2020/01/28/19/44/runner-4800810_960_720.jpg",
      "id": 2
    },
    {
      "title": "Lemur2345",
      "description": "Lemur1",
      "city": "Lemur",
      "image": "https://pixabay.com/get/52e7dc464856a514f1dc8460825668204022dfe05b517540762b79d2/lemur-4795249_640.jpg",
      "id": 3
    },
    {
      "title": "UPD1",
      "description": "UPD1",
      "city": "UPD1",
      "image": "https://cdn.pixabay.com/photo/2020/01/22/09/38/meeting-4784909_960_720.jpg",
      "id": 4
    },
    {
      "title": "Dev11 UPD1",
      "description": "Dev11UPD1",
      "city": "Київ UPD1",
      "image": "https://cdn.pixabay.com/photo/2020/01/26/20/14/computer-4795762_960_720.jpg",
      "id": 5
    },
    {
      "title": "Dev1ы1",
      "description": "Dev11ы1",
      "city": "City1ы1",
      "image": "https://cdn.pixabay.com/photo/2020/01/26/20/14/computer-4795762_960_720.jpg",
      "id": 6
    },
    {
      "title": "afdsы1",
      "description": "dfsdfы1",
      "city": "sdfы1",
      "image": "https://cdn.pixabay.com/photo/2020/01/26/20/14/computer-4795762_960_720.jpg",
      "id": 7
    },
    {
      "title": "adfы",
      "description": "dsfsdfdы",
      "city": "sfdsfы",
      "image": "https://cdn.pixabay.com/photo/2020/01/26/20/14/computer-4795762_960_720.jpg",
      "id": 8
    },
    {
      "title": "sadы1",
      "description": "adsы1",
      "city": "asdы1",
      "image": "https://cdn.pixabay.com/photo/2020/01/26/20/14/computer-4795762_960_720.jpg",
      "id": 10
    },
    {
      "title": "Title Title1",
      "description": "Description1 Description Description Description Description Description Description",
      "city": "City1",
      "image": "https://cdn.pixabay.com/photo/2020/01/26/20/14/computer-4795762_960_720.jpg",
      "id": 11
    },
    {
      "title": "Title1",
      "description": "Description1",
      "city": "City1",
      "image": "https://cdn.pixabay.com/photo/2020/01/26/20/14/computer-4795762_960_720.jpg",
      "id": 12
    },
    {
      "title": "Title1",
      "description": "Description1",
      "city": "City1",
      "image": "https://cdn.pixabay.com/photo/2020/01/26/20/14/computer-4795762_960_720.jpg",
      "id": 13
    },
    {
      "title": "Dev Title",
      "description": "Dev Description",
      "city": "Dev City",
      "image": "https://cdn.pixabay.com/photo/2020/01/27/10/24/pollution-4796858_960_720.jpg",
      "id": 14
    }
  ]
}